jupyter_drawio_export/__init__.py
jupyter_drawio_export/_version.py
jupyter_drawio_export/app.py
jupyter_drawio_export/constants.py
jupyter_drawio_export/handlers.py
jupyter_drawio_export/manager.py
jupyter_drawio_export/serverextension.py
jupyter_drawio_export/etc/jupyter-drawio-export.json
jupyter_drawio_export/tests/__init__.py
jupyter_drawio_export/tests/conftest.py
jupyter_drawio_export/tests/test_pdf.py
jupyter_drawio_export/tests/test_provision.py
jupyter_drawio_export/vendor/draw-image-export2/LICENSE
jupyter_drawio_export/vendor/draw-image-export2/README.md
jupyter_drawio_export/vendor/draw-image-export2/app.json
jupyter_drawio_export/vendor/draw-image-export2/export.js
jupyter_drawio_export/vendor/draw-image-export2/package.json
jupyter_drawio_export-0.8.0a1.data/data/etc/jupyter/jupyter_notebook_config.d/jupyter-drawio-export.json
jupyter_drawio_export-0.8.0a1.dist-info/LICENSE.txt
jupyter_drawio_export-0.8.0a1.dist-info/METADATA
jupyter_drawio_export-0.8.0a1.dist-info/WHEEL
jupyter_drawio_export-0.8.0a1.dist-info/entry_points.txt
jupyter_drawio_export-0.8.0a1.dist-info/top_level.txt
jupyter_drawio_export-0.8.0a1.dist-info/RECORD
