Metadata-Version: 2.1
Name: jupyter-drawio-export
Version: 0.8.0a1
Summary: PDF export for Drawio diagrams in Jupyter Notebook and JupyterLab
Home-page: https://github.com/deathbeds/jupyterlab-drawio
Author: jupyterlab-drawio Contributors
Author-email: ripxl@example.com
License: Apache-2.0
Platform: UNKNOWN
Classifier: Framework :: Jupyter
Classifier: Intended Audience :: Developers
Classifier: Intended Audience :: Information Technology
Classifier: License :: OSI Approved :: Apache Software License
Classifier: Programming Language :: Python
Requires-Python: >=3.6
Requires-Dist: jupyterlab
Requires-Dist: lxml
Requires-Dist: notebook (>=4.3.1)
Requires-Dist: pillow
Requires-Dist: pypdf2
Requires-Dist: requests-cache
